{
  "id": "hajj-frauen-gruppe",
  "slug": "hajj-frau-ohne-mahram",
  "category": "hajj",
  "subcategory": "",
  "question_de": "Hajj ohne Mahram in Gruppe?",
  "question_ar": "",
  "search_aliases": [
    "Hajj ohne Mahram in Gruppe?",
    "hajj frau ohne mahram"
  ],
  "context_de": "Für Frauen, die die Hajj-Pflicht erfüllen möchten, aber keinen Mahram (nahen männlichen Verwandten) haben, stellt sich die Frage nach der Erlaubnis einer Reise in einer Gruppe von vertrauenswürdigen Frauen.",
  "positions": [
    {
      "id": "pos-1",
      "label_de": "Erlaubt in einer vertrauenswürdigen Gruppe",
      "label_ar": "جوازه مع الرفقة الآمنة",
      "description_de": "Die Schafiiten und Malikiten erlauben die Hajj ohne Mahram, wenn die Reise in einer 'sicheren Gruppe' (Rufqa Amina) stattfindet, um die Sicherheit der Frau zu gewährleisten.",
      "scholars": [
        "Al-Shafi'i",
        "Malik ibn Anas"
      ],
      "madhabs": [
        "shafii",
        "maliki"
      ],
      "evidence_chain": [
        {
          "type": "hadith",
          "reference": "Sahih al-Bukhari",
          "text_de": "Es wird eine Zeit kommen, in der eine Frau von al-Hira nach Mekka reist und niemanden außer Allah fürchtet.",
          "explanation_de": "Dieser Hadith wird als Hinweis auf die Sicherheit als entscheidendes Kriterium interpretiert."
        }
      ]
    },
    {
      "id": "pos-2",
      "label_de": "Nicht erlaubt ohne Mahram",
      "label_ar": "عدم الجواز بغير محرم",
      "description_de": "Die Hanafiten und Hanbaliten bestehen strikt auf der Anwesenheit eines Mahram für jede Reise, die länger als drei Tage dauert, basierend auf dem wörtlichen Text der Hadithe.",
      "scholars": [
        "Abu Hanifa",
        "Ahmad ibn Hanbal"
      ],
      "madhabs": [
        "hanafi",
        "hanbali"
      ],
      "evidence_chain": [
        {
          "type": "hadith",
          "reference": "Sahih Muslim",
          "text_ar": "لا تسافر المرأة إلا مع ذي محرم",
          "text_de": "Eine Frau soll nur mit einem Mahram reisen.",
          "explanation_de": "Ein klares Verbot für jegliche Fernreisen ohne männliche Begleitung."
        }
      ]
    }
  ],
  "related_questions": [],
  "sources": [
    {
      "title": "Al-Mawsu'a al-Fiqhiyya",
      "author": "Kuwait Ministry of Awqaf",
      "url": "https://islamweb.net"
    }
  ]
}